reudom/__init__.py
reudom/case.py
reudom/cli.py
reudom/skip.py
reudom/TestRunner/HTMLTestRunner.py
reudom/TestRunner/__init__.py
reudom/TestRunner/html/__init__.py
reudom/TestRunner/html/charts_script.html
reudom/TestRunner/html/heading.html
reudom/TestRunner/html/mail.html
reudom/TestRunner/html/report.html
reudom/TestRunner/html/stylesheet.html
reudom/TestRunner/html/template.html
reudom/running/HTMLTestRunner.py
reudom/running/__init__.py
reudom/running/test_runner.py
reudom/testdata/User_Agent.py
reudom/testdata/__init__.py
reudom/testdata/aes.py
reudom/testdata/parameterizeds.py
reudom/testdata/timestamp.py
reudom-1.2.3.0.data/scripts/charts_script.html
reudom-1.2.3.0.data/scripts/heading.html
reudom-1.2.3.0.data/scripts/mail.html
reudom-1.2.3.0.data/scripts/report.html
reudom-1.2.3.0.data/scripts/stylesheet.html
reudom-1.2.3.0.data/scripts/template.html
reudom-1.2.3.0.dist-info/LICENSE
reudom-1.2.3.0.dist-info/METADATA
reudom-1.2.3.0.dist-info/WHEEL
reudom-1.2.3.0.dist-info/entry_points.txt
reudom-1.2.3.0.dist-info/top_level.txt
reudom-1.2.3.0.dist-info/RECORD
